README.md
setup.py
rrts/__init__.py
rrts/debugger.py
rrts/planner.py
rrts.egg-info/PKG-INFO
rrts.egg-info/SOURCES.txt
rrts.egg-info/dependency_links.txt
rrts.egg-info/requires.txt
rrts.egg-info/top_level.txt
test/test_collision_check.py
test/test_planner.py