Metadata-Version: 2.1
Name: rrts
Version: 1.0.8
Summary: RRTs Planners
Home-page: https://github.com/liespace/pyRRTs
Author: Gabel Liemann
Author-email: troubleli233@gmail.com
License: MIT
Platform: UNKNOWN
Classifier: Programming Language :: Python :: 2
Classifier: License :: OSI Approved :: MIT License
Classifier: Operating System :: OS Independent
